Metadata-Version: 2.1
Name: odoo12-addon-l10n-es-aeat-vat-prorrate
Version: 12.0.1.2.0
Summary: AEAT - Prorrata de IVA
Home-page: https://github.com/OCA/l10n-spain
Author: AvanzOSC, Tecnativa, Odoo Community Association (OCA)
Author-email: support@odoo-community.org
License: AGPL-3
Platform: UNKNOWN
Classifier: Programming Language :: Python
Classifier: Framework :: Odoo
Classifier: Framework :: Odoo :: 12.0
Classifier: License :: OSI Approved :: GNU Affero General Public License v3
Requires-Python: >=3.5
Requires-Dist: odoo12-addon-l10n-es-aeat-mod303
Requires-Dist: odoo (<12.1dev,>=12.0a)
